Metadata-Version: 2.1
Name: avala-sdk
Version: 0.0.17
Summary: Avala Client SDK
Home-page: https://github.com/avala-ai/avala-python
Author: Avala Developer
Author-email: developer@avala.ai
Classifier: Development Status :: 5 - Production/Stable
Classifier: Intended Audience :: Developers
Classifier: License :: OSI Approved :: MIT License
Classifier: Programming Language :: Python :: 3
Classifier: Programming Language :: Python :: 3.6
Classifier: Programming Language :: Python :: 3.7
Classifier: Programming Language :: Python :: 3.8
Classifier: Programming Language :: Python :: 3.9
Classifier: Operating System :: OS Independent
Requires-Python: >=3, <=3.9
Requires-Dist: requests
